flask_cognitologin/__init__.py
flask_cognitologin/cognitologin.py
flask_cognitologin-0.1.5.dist-info/AUTHORS.rst
flask_cognitologin-0.1.5.dist-info/LICENSE
flask_cognitologin-0.1.5.dist-info/METADATA
flask_cognitologin-0.1.5.dist-info/WHEEL
flask_cognitologin-0.1.5.dist-info/top_level.txt
flask_cognitologin-0.1.5.dist-info/RECORD
