Metadata-Version: 2.1
Name: flask-cognitologin
Version: 0.1.5
Summary: Flask-Login and AWS Cognito Integration
Home-page: https://github.com/ybenitezf/flask_cognitologin
Author: Yoel Benítez Fonseca
Author-email: ybenitezf@gmail.com
License: GNU General Public License v3
Keywords: flask_cognitologin
Platform: UNKNOWN
Classifier: Development Status :: 2 - Pre-Alpha
Classifier: Intended Audience :: Developers
Classifier: License :: OSI Approved :: GNU General Public License v3 (GPLv3)
Classifier: Natural Language :: English
Classifier: Programming Language :: Python :: 3
Classifier: Programming Language :: Python :: 3.6
Classifier: Programming Language :: Python :: 3.7
Classifier: Programming Language :: Python :: 3.8
Requires-Python: >=3.6
Requires-Dist: Flask (>=1.1.2)
Requires-Dist: python-jose (>=3.2.0)
Requires-Dist: requests (>=2.24.0)
